orthogonalization1411
