Metadata-Version: 1.0
Name: orthogonalization1411
Version: 2.8
Summary: Orthogonalization
Home-page: UNKNOWN
Author: Irving Chow
Author-email: 1624000827@qq.com
License: UNKNOWN
Platform: UNKNOWN
